tul_routing/__init__.py
tul_routing/config/__init__.py
tul_routing/config/config.py
tul_routing/constants/__init__.py
tul_routing/etl/Graph.py
tul_routing/etl/GraphChain.py
tul_routing/etl/__init__.py
tul_routing/etl/func_name.py
tul_routing/logging/__init__.py
tul_routing/parsing/__init__.py
tul_routing/parsing/abstract_parser.py
tul_routing/parsing/csv_parser.py
tul_routing/parsing/geojson_parser.py
tul_routing/parsing/gpx_parser.py
tul_routing/parsing/kml_parser.py
tul_routing/parsing/parse_type.py
tul_routing/parsing/route_parser.py
tul_routing/parsing/tcx_parser.py
tul_routing/processing/TulRouting.py
tul_routing/processing/__init__.py
tul_routing/processing/feature_extraction.py
tul_routing/processing/feature_pipeline.py
tul_routing/processing/matching_utils.py
tul_routing/processing/open_elevation_utils.py
tul_routing/processing/overpass_utils.py
tul_routing/typing/__init__.py
tul_routing/typing/df_segmented_type.py
tul_routing/typing/match_response_type.py
tul_routing/utils/__init__.py
tul_routing/utils/ensure_type.py
tul_routing/utils/geo_calculations.py
tul_routing/utils/time_utils.py
tul_routing/utils/timer.py
tul_routing/utils/town_cache.py
tul_routing-0.0.2.dist-info/LICENSE
tul_routing-0.0.2.dist-info/METADATA
tul_routing-0.0.2.dist-info/WHEEL
tul_routing-0.0.2.dist-info/top_level.txt
tul_routing-0.0.2.dist-info/RECORD
