Metadata-Version: 2.1
Name: tul-routing
Version: 0.0.2
Summary: TUL Routing project
Author-email: Jan Hybs <jan.hybs@tul.cz>, Radek Srb <radek.srb@tul.cz>, Jiri Vrany <jiri.vrany@tul.cz>
Project-URL: Homepage, https://github.com/janhybs/tul_routing
Project-URL: Bug Tracker, https://github.com/janhybs/tul_routing/issues
License-File: LICENSE
